{
   "owner": null,
   "codePut": "BEGIN\r\n    UP_STUDENT.UP_S_EMergancy_contact_IUD (\r\n        p_tran_type       => 'U'\r\n       ,P_PIDM            => :parm_user_pidm\r\n       ,P_PRIORITY        => :SPREMRG_PRIORITY\r\n       ,P_LAST_NAME       => :SPREMRG_LAST_NAME\r\n       ,P_FIRST_NAME      => :SPREMRG_FIRST_NAME\r\n       ,P_MI              => :SPREMRG_MI\r\n       ,P_STREET_LINE1    => :SPREMRG_STREET_LINE1\r\n       ,P_STREET_LINE2    => :SPREMRG_STREET_LINE2\r\n       ,P_STREET_LINE3    => :SPREMRG_STREET_LINE3\r\n       ,P_STREET_LINE4    => :SPREMRG_STREET_LINE4\r\n       ,P_CITY            => :SPREMRG_CITY\r\n       ,p_stat_code       => :SPREMRG_STAT_CODE\r\n       ,P_NATN_CODE       => :SPREMRG_NATN_CODE\r\n       ,P_ZIP             => :SPREMRG_ZIP\r\n       ,p_phone_area      => :SPREMRG_PHONE_AREA\r\n       ,P_PHONE_NUMBER    => :SPREMRG_PHONE_NUMBER\r\n       ,P_PHONE_EXT       => :SPREMRG_PHONE_EXT\r\n       ,P_RELT_CODE       => :SPREMRG_RELT_CODE\r\n       ,P_ATYP_CODE       => :SPREMRG_ATYP_CODE\r\n       ,p_email_address   => :EMAIL_ADDRESS\r\n       ,p_phone_type      => :TELEPHONE_TYPE\r\n       ,p_academic_ck     => :ACADEMIC_CK\r\n       ,p_finaid_ck       => :FINANCIAL_CK);\r\nEND;",
   "codeDelete": "begin \r\n\r\nUP_STUDENT.UP_S_EMergancy_contact_IUD ( p_tran_type      => 'D',\r\n        P_PIDM           => :parm_user_pidm,\r\n        P_PRIORITY       => :SPREMRG_PRIORITY,\r\n        p_rowid          => :id);\r\nend;",
   "virtualDomainRoles": [
      {
         "allowDelete": true,
         "allowPost": true,
         "allowPut": true,
         "roleName": "ALLROLES",
         "allowGet": true
      },
      {
         "allowDelete": true,
         "allowPost": true,
         "allowPut": true,
         "roleName": "STUDENT",
         "allowGet": true
      }
   ],
   "codeGet": "SELECT DISTINCT\r\n       ROWIDTOCHAR (a.ROWID)                                     \"id\"\r\n      ,a.\"SPREMRG_PIDM\"\r\n      ,a.\"SPREMRG_PRIORITY\"\r\n      ,a.\"SPREMRG_LAST_NAME\"\r\n      ,a.\"SPREMRG_FIRST_NAME\"\r\n      ,a.\"SPREMRG_MI\"\r\n      ,a.\"SPREMRG_STREET_LINE1\"\r\n      ,a.\"SPREMRG_STREET_LINE2\"\r\n      ,a.\"SPREMRG_STREET_LINE3\"\r\n      ,a.\"SPREMRG_CITY\"\r\n      ,a.\"SPREMRG_STAT_CODE\"\r\n      ,a.\"SPREMRG_NATN_CODE\"\r\n      ,a.\"SPREMRG_ZIP\"\r\n      ,a.\"SPREMRG_PHONE_AREA\"\r\n      ,a.\"SPREMRG_PHONE_NUMBER\"\r\n      ,a.\"SPREMRG_PHONE_EXT\"\r\n      ,a.\"SPREMRG_RELT_CODE\"\r\n      ,a.\"SPREMRG_ACTIVITY_DATE\"\r\n      ,a.\"SPREMRG_ATYP_CODE\"\r\n      ,a.\"SPREMRG_DATA_ORIGIN\"\r\n      ,a.\"SPREMRG_USER_ID\"\r\n      ,a.\"SPREMRG_SURNAME_PREFIX\"\r\n      ,a.\"SPREMRG_CTRY_CODE_PHONE\"\r\n      ,a.\"SPREMRG_HOUSE_NUMBER\"\r\n      ,a.\"SPREMRG_STREET_LINE4\"\r\n      ,a.\"SPREMRG_SURROGATE_ID\"\r\n      ,a.\"SPREMRG_VERSION\"\r\n      ,a.\"SPREMRG_VPDI_CODE\"\r\n      ,a.\"SPREMRG_GUID\"\r\n      ,a.\"SPREMRG_PHONE_AVAIL_GUID\"\r\n      ,a.\"SPREMRG_EMERGENCY_GUID\"\r\n      ,a1.gorsdav_value.accessVARCHAR2 ()                        EMAIL_ADDRESS\r\n      ,a2.gorsdav_value.accessVARCHAR2 ()                        TELEPHONE_TYPE\r\n      ,MAX (NVL (SORFOLK_PARENT_EMPLOYER, 'NO'))\r\n           OVER (PARTITION BY SPREMRG_PIDM, SPREMRG_PRIORITY)    ACADEMIC_CK\r\n      ,MAX (NVL (SORFOLK_PARENT_JOB_TITLE, 'NO'))\r\n           OVER (PARTITION BY SPREMRG_PIDM, SPREMRG_PRIORITY)    FINANCIAL_CK\r\n  FROM spremrg  a\r\n      ,gorsdav  a1\r\n      ,gorsdav  a2\r\n      ,sorfolk  folk\r\n WHERE     1 = 1\r\n       AND spremrg_pidm = :parm_user_pidm\r\n       AND (spremrg_priority = :spremrg_priority OR :spremrg_priority IS NULL)\r\n       AND a1.gorsdav_table_name(+) = 'SPREMRG'\r\n       AND a1.gorsdav_attr_name(+) = 'EMAIL_ADDRESS'\r\n       AND a1.gorsdav_pk_parenttab(+) =\r\n           SPREMRG_pidm || CHR (1) || SPREMRG_PRIORITY\r\n       AND a2.gorsdav_table_name(+) = 'SPREMRG'\r\n       AND a2.gorsdav_attr_name(+) = 'TELEPHONE_TYPE'\r\n       AND a2.gorsdav_pk_parenttab(+) =\r\n           SPREMRG_pidm || CHR (1) || SPREMRG_PRIORITY\r\n       AND folk.sorfolk_pidm(+) = SPREMRG_pidm\r\n       AND folk.SORFOLK_PARENT_LAST(+) = SPREMRG_LAST_NAME\r\n       AND folk.SORFOLK_PARENT_FIRST(+) = SPREMRG_FIRST_NAME\r\n       AND NVL (folk.SORFOLK_PARENT_MI(+), '@') = NVL (SPREMRG_MI, '@')\r\n       AND folk.SORFOLK_RELT_CODE(+) = SPREMRG_RELT_CODE;",
   "typeOfCode": "S",
   "fileTimestamp": "2022-02-14T15:25:25Z",
   "serviceName": "UP_S_SPREMRG_SDE_PRIROTY",
   "codePost": "BEGIN\r\n    UP_STUDENT.UP_S_EMergancy_contact_IUD (\r\n        p_tran_type       => 'I'\r\n       ,P_PIDM            => :parm_user_pidm\r\n       ,P_PRIORITY        => :SPREMRG_PRIORITY\r\n       ,P_LAST_NAME       => :SPREMRG_LAST_NAME\r\n       ,P_FIRST_NAME      => :SPREMRG_FIRST_NAME\r\n       ,P_MI              => :SPREMRG_MI\r\n       ,P_STREET_LINE1    => :SPREMRG_STREET_LINE1\r\n       ,P_STREET_LINE2    => :SPREMRG_STREET_LINE2\r\n       ,P_STREET_LINE3    => :SPREMRG_STREET_LINE3\r\n       ,P_STREET_LINE4    => :SPREMRG_STREET_LINE4\r\n       ,P_CITY            => :SPREMRG_CITY\r\n       ,p_stat_code       => :SPREMRG_STAT_CODE\r\n       ,P_NATN_CODE       => :SPREMRG_NATN_CODE\r\n       ,P_ZIP             => :SPREMRG_ZIP\r\n       ,p_phone_area      => :SPREMRG_PHONE_AREA\r\n       ,P_PHONE_NUMBER    => :SPREMRG_PHONE_NUMBER\r\n       ,P_PHONE_EXT       => :SPREMRG_PHONE_EXT\r\n       ,P_RELT_CODE       => :SPREMRG_RELT_CODE\r\n       ,P_ATYP_CODE       => :SPREMRG_ATYP_CODE\r\n       ,p_email_address   => :EMAIL_ADDRESS\r\n       ,p_phone_type      => :TELEPHONE_TYPE\r\n       ,p_academic_ck     => :ACADEMIC_CK\r\n       ,p_finaid_ck       => :FINANCIAL_CK);\r\nEND;",
   "developerSecurity": []
}